{
  "id": "hair-owner-lp",
  "type": "booking-lp",
  "title": "美容室オーナー向け・予約管理自動化LP",
  "hero": {
    "headline": "予約管理のストレスをゼロへ。",
    "subheadline": "もう「電話対応」「ダブルブッキング」「空き枠の反映漏れ」に悩まない美容室へ。",
    "badge": "美容室オーナー向け予約ツール",
    "ctaLabel": "今すぐLINEで予約管理を自動化する"
  },
  "benefits": [
    "施術中に電話応対で手を止めなくていい",
    "LINEから自動で予約受付ができる",
    "予約枠を登録するだけで空き状況が自動反映",
    "二重予約防止ロックでミスゼロ運営",
    "1人オペでも運営が回る仕組み化"
  ],
  "beforeAfter": {
    "title": "導入前と導入後の違い",
    "beforeItems": [
      "予約の電話対応で施術が中断される",
      "紙やノートでの管理で記入ミスが不安",
      "空き枠の管理がめんどくさい",
      "SNSからの予約導線が弱い"
    ],
    "afterItems": [
      "LINEで自動受付されるので施術に集中できる",
      "予約枠は一括登録＆自動管理でミス削減",
      "空き枠はカレンダーと連動して自動反映",
      "InstagramやLINEからそのまま予約に繋がる"
    ]
  },
  "pricing": {
    "title": "料金プラン（例）",
    "note": "※ サロンの規模に合わせて柔軟に変更可能です。",
    "plans": [
      {
        "name": "ライトプラン",
        "price": "月額 5,000円〜",
        "description": "LINE予約 + カレンダー連携",
        "features": [
          "LINEからの自動予約受付",
          "基本的な予約枠管理",
          "スマホ対応の予約画面"
        ],
        "recommended": false
      },
      {
        "name": "スタンダードプラン",
        "price": "月額 8,000円〜",
        "description": "予約枠管理 + リピート導線強化",
        "features": [
          "ライトプランの全機能",
          "リピート導線を意識した予約導線",
          "簡単な分析（人気メニュー・時間帯）"
        ],
        "recommended": true
      },
      {
        "name": "プロプラン",
        "price": "月額 10,000円〜",
        "description": "小規模サロンの“予約担当者”代わりに",
        "features": [
          "スタンダードの全機能",
          "Slack通知などの運営向け通知",
          "今後の自動決済・自動営業機能の優先提供"
        ],
        "recommended": false
      }
    ]
  },
  "reviews": {
    "title": "ご利用イメージ（サロンオーナーの声・サンプル）",
    "items": [
      {
        "name": "1人で切り盛りする美容室オーナー様",
        "quote": "施術中に予約の電話が鳴らなくなっただけで本当に助かってます。LINEで勝手に予約が入るので、カットに集中できる時間が増えました。"
      },
      {
        "name": "郊外の小さなサロンオーナー様",
        "quote": "今までノートで管理していたときより、予約ミスがゼロに。1人営業でも“ちゃんとしたサロン”として見られるようになった気がします。"
      }
    ],
    "note": "※ 実際の導入サロンの声が集まり次第、差し替え・追記できます。"
  },
  "faq": {
    "title": "よくあるご質問",
    "items": [
      {
        "question": "導入は難しくないですか？",
        "answer": "基本的には「予約枠を入力するだけ」で自動化できます。スマホでLINEを使える方なら、そのまま使えるくらいの難易度です。"
      },
      {
        "question": "決済機能は必須ですか？",
        "answer": "決済機能なしでもご利用可能です。まずは予約の自動化からスタートして、必要に応じて今後の自動決済機能を追加できます。"
      },
      {
        "question": "月途中の解約はできますか？",
        "answer": "はい、いつでも解約可能です。まずは小さく試していただいて、合うと感じたら継続いただく形を想定しています。"
      }
    ]
  },
  "policy": {
    "title": "キャンセルについて（例）",
    "body": [
      "・当日キャンセル：キャンセル料は原則いただきません。",
      "・無断キャンセルが複数回続く場合は、次回以降の予約をお断りする場合があります。",
      "・美容室ごとの運用ルールに合わせて柔軟に変更可能です。"
    ]
  },
  "cta": {
    "primary": {
      "label": "今すぐLINEで予約管理を自動化する",
      "subtext": "まずは空き時間の予約受付だけでもOKです。1人サロンでも無理なく始められます。"
    },
    "secondary": {
      "label": "導入の相談をしてみる",
      "subtext": "「うちの店でも使えるか不安」という方は、まずは相談ベースでお話しください。"
    }
  }
}
